aurora/__init__.py
aurora/apps.py
aurora/checks.py
aurora/cli.py
aurora/ddt_panels.py
aurora/exceptions.py
aurora/py.typed
aurora/state.py
aurora/tasks.py
aurora/version.py
aurora/LOCALE/en/LC_MESSAGES/django.mo
aurora/LOCALE/en/LC_MESSAGES/django.po
aurora/LOCALE/en/LC_MESSAGES/djangojs.mo
aurora/LOCALE/en/LC_MESSAGES/djangojs.po
aurora/LOCALE/uk_UA/LC_MESSAGES/django.mo
aurora/LOCALE/uk_UA/LC_MESSAGES/django.po
aurora/LOCALE/uk_UA/LC_MESSAGES/djangojs.mo
aurora/LOCALE/uk_UA/LC_MESSAGES/djangojs.po
aurora/administration/__init__.py
aurora/administration/apps.py
aurora/administration/forms.py
aurora/administration/hijack.py
aurora/administration/panels.py
aurora/administration/static/admin/filter_table.js
aurora/administration/static/admin/filter_table.min.js
aurora/administration/static/admin/css/aurora_admin.css
aurora/administration/static/admin/css/aurora_admin.css.map
aurora/administration/static/admin/css/aurora_admin.scss
aurora/api/__init__.py
aurora/api/router.py
aurora/api/urls.py
aurora/api/serializers/__init__.py
aurora/api/serializers/base.py
aurora/api/serializers/field.py
aurora/api/serializers/flatpage.py
aurora/api/serializers/form.py
aurora/api/serializers/org.py
aurora/api/serializers/project.py
aurora/api/serializers/record.py
aurora/api/serializers/registration.py
aurora/api/serializers/template.py
aurora/api/serializers/validator.py
aurora/api/static/api/style.css
aurora/api/static/api/style.css.map
aurora/api/static/api/style.scss
aurora/api/templates/rest_framework/admin.html
aurora/api/templates/rest_framework/api.html
aurora/api/templates/rest_framework/base.html
aurora/api/templates/rest_framework/login.html
aurora/api/templates/rest_framework/login_base.html
aurora/api/templates/rest_framework/raw_data_form.html
aurora/api/templates/rest_framework/schema.js
aurora/api/templates/rest_framework/schema.min.js
aurora/api/templates/rest_framework/admin/detail.html
aurora/api/templates/rest_framework/admin/dict_value.html
unicef_hope_aurora-1.7.dev639.dist-info/METADATA
unicef_hope_aurora-1.7.dev639.dist-info/WHEEL
unicef_hope_aurora-1.7.dev639.dist-info/entry_points.txt
unicef_hope_aurora-1.7.dev639.dist-info/licenses/LICENSE
unicef_hope_aurora-1.7.dev639.dist-info/RECORD
