Metadata-Version: 2.4
Name: unicef-hope-aurora
Version: 1.7.dev639
Project-URL: Documentation, https://unicef.github.io/hope-aurora/
Project-URL: Homepage, https://github.com/unicef/hope-aurora
Project-URL: Issues, https://github.com/unicef/hope-aurora/issues
Project-URL: Repository, https://github.com/unicef/hope-aurora
Author-email: sax <s.apostolico@gmail.com>, Domenico DiNicola <dom.dinicola@gmail.com>
License: MIT
License-File: LICENSE
Classifier: Programming Language :: Python :: 3 :: Only
Classifier: Programming Language :: Python :: 3.12
Classifier: Programming Language :: Python :: 3.13
Requires-Python: >=3.12
Requires-Dist: beautifulsoup4
Requires-Dist: celery
Requires-Dist: channels-redis
Requires-Dist: channels[daphne]
Requires-Dist: cryptography>=45
Requires-Dist: django-admin-extra-buttons>=2.1.1
Requires-Dist: django-admin-ordering
Requires-Dist: django-admin-sync>=0.9
Requires-Dist: django-adminactions
Requires-Dist: django-adminfilters
Requires-Dist: django-anymail[mailjet]
Requires-Dist: django-appconf
Requires-Dist: django-bitfield
Requires-Dist: django-click
Requires-Dist: django-concurrency
Requires-Dist: django-constance
Requires-Dist: django-cors-headers
Requires-Dist: django-csp
Requires-Dist: django-debug-toolbar
Requires-Dist: django-filter
Requires-Dist: django-flags
Requires-Dist: django-front-door
Requires-Dist: django-hijack
Requires-Dist: django-import-export
Requires-Dist: django-jsoneditor
Requires-Dist: django-mdeditor
Requires-Dist: django-mptt
Requires-Dist: django-picklefield
Requires-Dist: django-pwa
Requires-Dist: django-redis
Requires-Dist: django-regex
Requires-Dist: django-reversion
Requires-Dist: django-reversion-compare
Requires-Dist: django-simple-captcha
Requires-Dist: django-simple-math-captcha
Requires-Dist: django-smart-admin>=3
Requires-Dist: django-smart-env
Requires-Dist: django-strategy-field>=3.2.1
Requires-Dist: django-stubs[compatible-mypy]
Requires-Dist: django-sysinfo
Requires-Dist: django-tinymce
Requires-Dist: django==5.2.*
Requires-Dist: djangorestframework
Requires-Dist: djangorestframework-datatables
Requires-Dist: dukpy>=0.5
Requires-Dist: faker
Requires-Dist: jmespath
Requires-Dist: jsonpickle
Requires-Dist: markdown
Requires-Dist: msgpack>=1.1
Requires-Dist: natural-keys
Requires-Dist: pillow
Requires-Dist: psycopg2-binary
Requires-Dist: pygments
Requires-Dist: pyquery
Requires-Dist: qrcode
Requires-Dist: sentry-sdk
Requires-Dist: social-auth-app-django
Requires-Dist: sqlparse
